anomalies/__init__.py
anomalies/anomaly.py
anomalies-0.2.8.dist-info/licenses/LICENSE
anomalies-0.2.8.dist-info/METADATA
anomalies-0.2.8.dist-info/WHEEL
anomalies-0.2.8.dist-info/top_level.txt
anomalies-0.2.8.dist-info/RECORD
