Metadata-Version: 2.4
Name: anomalies
Version: 0.2.8
Summary: Anomaly cancellation
Home-page: https://github.com/restrepo/anomalies
Author: restrepo
Author-email: restrepo@udea.edu.co
License: BSD
Requires-Python: >=3.12
License-File: LICENSE
Requires-Dist: numpy>=1.23.0; python_version == "3.12"
Requires-Dist: numpy>=1.24.0; python_version == "3.13"
Requires-Dist: numpy>=1.25.0; python_version == "3.14"
Requires-Dist: numpy>=1.26.0; python_version == "3.15"
Dynamic: author
Dynamic: author-email
Dynamic: description
Dynamic: description-content-type
Dynamic: home-page
Dynamic: license
Dynamic: license-file
Dynamic: requires-dist
Dynamic: requires-python
Dynamic: summary
